pvcheetah/LICENSE
pvcheetah/__init__.py
pvcheetah/_cheetah.py
pvcheetah/_factory.py
pvcheetah/_util.py
pvcheetah/lib/common/cheetah_params.pv
pvcheetah/lib/linux/x86_64/libpv_cheetah.so
pvcheetah/lib/mac/arm64/libpv_cheetah.dylib
pvcheetah/lib/mac/x86_64/libpv_cheetah.dylib
pvcheetah/lib/raspberry-pi/cortex-a53/libpv_cheetah.so
pvcheetah/lib/raspberry-pi/cortex-a53-aarch64/libpv_cheetah.so
pvcheetah/lib/raspberry-pi/cortex-a72/libpv_cheetah.so
pvcheetah/lib/raspberry-pi/cortex-a72-aarch64/libpv_cheetah.so
pvcheetah/lib/raspberry-pi/cortex-a76/libpv_cheetah.so
pvcheetah/lib/raspberry-pi/cortex-a76-aarch64/libpv_cheetah.so
pvcheetah/lib/windows/amd64/libpv_cheetah.dll
pvcheetah/lib/windows/amd64/pv_ypu_impl_cuda.dll
pvcheetah/lib/windows/arm64/libpv_cheetah.dll
pvcheetah-3.0.1.dist-info/METADATA
pvcheetah-3.0.1.dist-info/WHEEL
pvcheetah-3.0.1.dist-info/top_level.txt
pvcheetah-3.0.1.dist-info/RECORD
