Metadata-Version: 2.4
Name: pvcheetah
Version: 3.0.1
Summary: Cheetah Speech-to-Text Engine.
Home-page: https://github.com/Picovoice/cheetah
Author: Picovoice
Author-email: hello@picovoice.ai
Keywords: Speech-to-Text,Speech Recognition,Voice Recognition,ASR,Automatic Speech Recognition
Classifier: Development Status :: 5 - Production/Stable
Classifier: Intended Audience :: Developers
Classifier: License :: OSI Approved :: Apache Software License
Classifier: Operating System :: OS Independent
Classifier: Programming Language :: Python :: 3
Classifier: Topic :: Multimedia :: Sound/Audio :: Speech
Requires-Python: >=3.9
Dynamic: author
Dynamic: author-email
Dynamic: classifier
Dynamic: description
Dynamic: description-content-type
Dynamic: home-page
Dynamic: keywords
Dynamic: requires-python
Dynamic: summary
